[{"title":"新增raspbian、rubygems镜像","date":"2017-10-29T05:48:02.000Z","tags":[{"name":"raspbian","slug":"raspbian","permalink":"https://mirrors.as/tags/raspbian/"},{"name":"rubygems","slug":"rubygems","permalink":"https://mirrors.as/tags/rubygems/"}],"abbrlink":"a6cbe54a"},{"title":"服务器维护通知","date":"2017-10-25T11:34:59.000Z","tags":[{"name":"服务器","slug":"服务器","permalink":"https://mirrors.as/tags/服务器/"},{"name":"维护","slug":"维护","permalink":"https://mirrors.as/tags/维护/"}],"abbrlink":"bf673f25"},{"title":"Git服务器维护通知","date":"2017-10-01T15:00:52.000Z","tags":[{"name":"git","slug":"git","permalink":"https://mirrors.as/tags/git/"},{"name":"维护","slug":"维护","permalink":"https://mirrors.as/tags/维护/"}],"abbrlink":"61042953"},{"title":"镜像服务器维护通知","date":"2017-10-01T05:08:56.000Z","tags":[{"name":"维护","slug":"维护","permalink":"https://mirrors.as/tags/维护/"},{"name":"信息办","slug":"信息办","permalink":"https://mirrors.as/tags/信息办/"}],"abbrlink":"4c68fcaa"},{"title":"新增CPAN等13个开源镜像","date":"2017-09-23T16:21:07.000Z","tags":[{"name":"镜像","slug":"镜像","permalink":"https://mirrors.as/tags/镜像/"},{"name":"新增","slug":"新增","permalink":"https://mirrors.as/tags/新增/"}],"abbrlink":"c6703ce"}]